tigol/__init__.py
tigol/auth.py
tigol/client.py
tigol/decorators.py
tigol/models.py
tigol/session.py
tigol-1.0.1.dist-info/METADATA
tigol-1.0.1.dist-info/WHEEL
tigol-1.0.1.dist-info/licenses/LICENSE
tigol-1.0.1.dist-info/RECORD
